<?xml version="1.0" encoding="utf-8"?>
<ArrayOfCall xmlns:xsi="http://www.w3.org/2001/XMLSchema-instance" xmlns:xsd="http://www.w3.org/2001/XMLSchema">
  <Call>
    <Id>1000</Id>
    <CallType>desert</CallType>
    <Description>I want to prepare a lemomCake</Description>
    <FullAdress>orange 56</FullAdress>
    <Latitude>-45.18307417360392</Latitude>
    <Longitude>-23.71406276966954</Longitude>
    <OpeningCallTime>2025-01-23T13:39:48</OpeningCallTime>
    <MaxTimeToEnd>2025-02-06T13:39:48</MaxTimeToEnd>
  </Call>
  <Call>
    <Id>1001</Id>
    <CallType>pastry</CallType>
    <Description>Hi mazal tov! i prepare a creamy champinion pasta</Description>
    <FullAdress>ananas 12</FullAdress>
    <Latitude>-53.90829145046816</Latitude>
    <Longitude>11.113538674470533</Longitude>
    <OpeningCallTime>2025-01-24T14:39:48</OpeningCallTime>
    <MaxTimeToEnd>2025-02-07T13:39:48</MaxTimeToEnd>
  </Call>
  <Call>
    <Id>1002</Id>
    <CallType>mainMeal</CallType>
    <Description>harbe nahat! i bring a cheesy salad</Description>
    <FullAdress>kiwi 88</FullAdress>
    <Latitude>71.65155696257605</Latitude>
    <Longitude>80.5612056725094</Longitude>
    <OpeningCallTime>2025-01-25T15:39:48</OpeningCallTime>
    <MaxTimeToEnd>2025-02-08T13:39:48</MaxTimeToEnd>
  </Call>
  <Call>
    <Id>1003</Id>
    <CallType>salade</CallType>
    <Description>oh a new baby! i bring the family a chocolate pai</Description>
    <FullAdress>apple 2</FullAdress>
    <Latitude>-39.211842796283584</Latitude>
    <Longitude>-8.225649069115036</Longitude>
    <OpeningCallTime>2025-01-26T13:39:48</OpeningCallTime>
    <MaxTimeToEnd>2025-02-09T13:39:48</MaxTimeToEnd>
  </Call>
</ArrayOfCall>